gmagent/__init__.py
gmagent/app/__init__.py
gmagent/app/config.py
gmagent/app/fastapi_server.py
gmagent/app/mcp_server.py
gmagent/app/api/__init__.py
gmagent/app/api/core.py
gmagent/app/core/__init__.py
gmagent/app/models/__init__.py
gmagent/app/services/__init__.py
gmagent-0.1.10.dist-info/METADATA
gmagent-0.1.10.dist-info/WHEEL
gmagent-0.1.10.dist-info/entry_points.txt
gmagent-0.1.10.dist-info/RECORD
