Metadata-Version: 2.4
Name: gmagent
Version: 0.1.10
Summary: FastAPI and MCP services for GM API integration
Author-email: bidong <liao.bidong@myquant.cn>
Requires-Python: >=3.10
Requires-Dist: fastapi>=0.109.0
Requires-Dist: gm>=1.0.0
Requires-Dist: mcp[cli]>=0.1.0
Requires-Dist: numpy>=1.26.0
Requires-Dist: pandas>=2.2.0
Requires-Dist: polars>=0.20.0
Requires-Dist: pydantic-settings>=2.1.0
Requires-Dist: pydantic>=2.6.0
Requires-Dist: uvicorn>=0.27.0
Provides-Extra: test
Requires-Dist: httpx>=0.27.0; extra == 'test'
Requires-Dist: pytest-mock>=3.12.0; extra == 'test'
Requires-Dist: pytest>=8.0.0; extra == 'test'
